clip_jax/__init__.py
clip_jax/data.py
clip_jax/maxtext_model.ipynb
clip_jax/modeling.py
clip_jax/partitions.py
clip_jax/tokenizer.py
clip_jax/utils.py
clip_jax/wandb_utils.py
clip_jax/maxtext/README.md
clip_jax/maxtext/__init__.py
clip_jax/maxtext/accelerator_to_spec_map.py
clip_jax/maxtext/checkpointing.py
clip_jax/maxtext/common_types.py
clip_jax/maxtext/inference_utils.py
clip_jax/maxtext/max_logging.py
clip_jax/maxtext/max_utils.py
clip_jax/maxtext/multihost_dataloading.py
clip_jax/maxtext/pyconfig.py
clip_jax/maxtext/sequence_packing.py
clip_jax/maxtext/tokenizer.py
clip_jax/maxtext/input_pipeline/_grain_data_processing.py
clip_jax/maxtext/input_pipeline/_grain_operations.py
clip_jax/maxtext/input_pipeline/_grain_tokenizer.py
clip_jax/maxtext/input_pipeline/_hf_data_processing.py
clip_jax/maxtext/input_pipeline/_input_pipeline_utils.py
clip_jax/maxtext/input_pipeline/_tfds_data_processing.py
clip_jax/maxtext/input_pipeline/_tfds_data_processing_c4_mlperf.py
clip_jax/maxtext/input_pipeline/input_pipeline_interface.py
clip_jax/maxtext/layers/attentions.py
clip_jax/maxtext/layers/embeddings.py
clip_jax/maxtext/layers/gemma.py
clip_jax/maxtext/layers/gpt3.py
clip_jax/maxtext/layers/initializers.py
clip_jax/maxtext/layers/linears.py
clip_jax/maxtext/layers/llama2.py
clip_jax/maxtext/layers/mistral.py
clip_jax/maxtext/layers/models.py
clip_jax/maxtext/layers/normalizations.py
clip_jax/maxtext/layers/pipeline.py
clip_jax/maxtext/layers/quantizations.py
clip_jax/maxtext/layers/simple_layer.py
clip_jax-0.0.6.dist-info/METADATA
clip_jax-0.0.6.dist-info/WHEEL
clip_jax-0.0.6.dist-info/licenses/LICENSE.md
clip_jax-0.0.6.dist-info/RECORD
