Metadata-Version: 2.4
Name: clip-jax
Version: 0.0.6
Summary: Training of CLIP in JAX
License-Expression: Apache-2.0
License-File: LICENSE.md
Requires-Dist: aqtp
Requires-Dist: flax
Requires-Dist: jax
Requires-Dist: numpy
Requires-Dist: orbax-checkpoint
Requires-Dist: transformers
Requires-Dist: wandb
Provides-Extra: dev
Requires-Dist: optax; extra == 'dev'
Requires-Dist: precondition-opt; extra == 'dev'
Requires-Dist: tqdm; extra == 'dev'
